LICENSE
MANIFEST.in
README
a.py
bench.py
ez_setup.py
setup.py
shibazuke.c
shibazuke.pyx
testshibazuke.py
Shibazuke.egg-info/PKG-INFO
Shibazuke.egg-info/SOURCES.txt
Shibazuke.egg-info/dependency_links.txt
Shibazuke.egg-info/top_level.txt
docs/Makefile
docs/conf.py
docs/index.rst
docs/make.bat
py/pyshibazuke.py