Metadata-Version: 1.0
Name: Shibazuke
Version: 0.1.1
Summary: Fast object serializer for Python
Home-page: https://launchpad.net/shibazuke
Author: Atsuo Ishimoto
Author-email: ishimoto@gembook.org
License: MIT License
Platform: any
Classifier: Intended Audience :: Developers
Classifier: License :: OSI Approved :: MIT License
Classifier: Programming Language :: Python
Classifier: Topic :: Software Development :: Libraries :: Python Modules
